{
  "resourceType": "CarePlan",
  "id": "Fall5-Tumorboard-Neoadjuvant",
  "meta": {
    "profile": [
      "https://www.senologie.org/fhir/StructureDefinition/senologie-tumorboard-empfehlung"
    ]
  },
  "period": {
    "start": "2025-01-30"
  },
  "addresses": [
    {
      "reference": "Condition/Fall5-Diagnose-Mammakarzinom"
    }
  ],
  "activity": [
    {
      "detail": {
        "code": {
          "coding": [
            {
              "code": "385786002",
              "system": "http://snomed.info/sct",
              "display": "Chemotherapy care (regime/therapy)"
            }
          ],
          "text": "Neoadjuvant: EC x4, dann Docetaxel + Trastuzumab x4"
        },
        "kind": "MedicationRequest",
        "status": "scheduled"
      }
    },
    {
      "detail": {
        "code": {
          "coding": [
            {
              "code": "387713003",
              "system": "http://snomed.info/sct",
              "display": "Surgical procedure (procedure)"
            }
          ],
          "text": "BET rechts + Sentinel-LK-Biopsie"
        },
        "kind": "ServiceRequest",
        "status": "scheduled"
      }
    },
    {
      "detail": {
        "code": {
          "coding": [
            {
              "code": "416608005",
              "system": "http://snomed.info/sct",
              "display": "Drug therapy"
            }
          ],
          "text": "Trastuzumab Erhaltung 1 Jahr"
        },
        "kind": "MedicationRequest",
        "status": "scheduled"
      }
    },
    {
      "detail": {
        "code": {
          "coding": [
            {
              "code": "108290001",
              "system": "http://snomed.info/sct",
              "display": "Radiation oncology AND/OR radiotherapy (procedure)"
            }
          ],
          "text": "Adjuvante Ganzbrustbestrahlung"
        },
        "kind": "ServiceRequest",
        "status": "scheduled"
      }
    },
    {
      "detail": {
        "code": {
          "coding": [
            {
              "code": "169413002",
              "system": "http://snomed.info/sct",
              "display": "Hormone therapy (procedure)"
            }
          ],
          "text": "Letrozol für 5 Jahre"
        },
        "kind": "MedicationRequest",
        "status": "scheduled"
      }
    }
  ],
  "status": "active",
  "intent": "plan",
  "title": "Tumorboard-Empfehlung Monika Braun — Erstvorstellung",
  "description": "Empfehlung: Neoadjuvante Chemotherapie EC x4, dann Docetaxel + Trastuzumab x4. Anschließend BET rechts + SLNB. Adjuvant: Trastuzumab Erhaltung 1 Jahr, Ganzbrustbestrahlung, Letrozol.",
  "subject": {
    "reference": "Patient/Fall5-Patient-Monika-Braun"
  }
}
