{
  "resourceType": "CodeSystem",
  "status": "draft",
  "content": "complete",
  "name": "CSSenologieDiagnosesicherung",
  "id": "cs-senologie-diagnosesicherung",
  "title": "CodeSystem Diagnosesicherung",
  "description": "Diagnosesicherung gemäß oBDS (Onkologischer Basisdatensatz)",
  "url": "http://fhir.bih-charite.de/kds-senologie/CodeSystem/cs-senologie-diagnosesicherung",
  "concept": [
    {
      "code": "1",
      "display": "Klinisch ohne weitere Spezifizierung",
      "definition": "Klinische Angaben (ohne die nachfolgenden Kategorien)"
    },
    {
      "code": "2",
      "display": "Klinische Diagnostik",
      "definition": "Spezifische Diagnostik wie Endoskopie, bildgebende Verfahren, Ultraschall, explorative Eingriffe"
    },
    {
      "code": "3",
      "display": "Chirurgisch/Autopsie ohne Histologie",
      "definition": "Chirurgische Eingriffe (wie Laparotomie) und Autopsie, aber ohne Gewebsuntersuchung"
    },
    {
      "code": "4",
      "display": "Spezifische Tumormarker",
      "definition": "Biochemische und/oder immunologische Marker, die für einen bestimmten Tumorsitz spezifisch sind"
    },
    {
      "code": "5",
      "display": "Zytologie",
      "definition": "Untersuchung von Zellen aus primärem oder sekundärem Sitz, einschließlich Aspiraten"
    },
    {
      "code": "6",
      "display": "Histologie einer Metastase",
      "definition": "Histologische Untersuchung von Metastasengewebe"
    },
    {
      "code": "7",
      "display": "Histologie Primärtumor",
      "definition": "Histologische Untersuchung eines Primärtumors"
    },
    {
      "code": "7.1",
      "display": "Histologie nach Operation",
      "definition": "Histologische Untersuchung nach operativer Entfernung"
    },
    {
      "code": "7.2",
      "display": "Histologie nach Biopsie",
      "definition": "Histologische Untersuchung nach Biopsie"
    },
    {
      "code": "7.3",
      "display": "Histologie nach Autopsie",
      "definition": "Histologische Untersuchung nach Autopsie"
    },
    {
      "code": "8",
      "display": "Genetisch/Molekularbiologisch",
      "definition": "Zytogenetische und/oder molekularbiologische Untersuchung"
    },
    {
      "code": "9",
      "display": "Unbekannt",
      "definition": "Diagnosesicherung unbekannt"
    }
  ],
  "caseSensitive": true,
  "count": 12
}
