{
  "resourceType": "ConceptMap",
  "id": "cm-sct-to-obds-therapieart",
  "url": "http://fhir.bih-charite.de/kds-senologie/ConceptMap/cm-sct-to-obds-therapieart",
  "title": "SNOMED CT to oBDS Therapieart",
  "description": "Mapping von SNOMED CT Therapieart-Codes zu oBDS Therapieart (CH, HO, IM, ZS, SO, ST)",
  "group": [
    {
      "element": [
        {
          "target": [
            {
              "code": "CH",
              "display": "Chemotherapie",
              "equivalence": "equivalent"
            }
          ],
          "code": "367336001",
          "display": "Chemotherapy (procedure)"
        },
        {
          "target": [
            {
              "code": "HO",
              "display": "Hormontherapie",
              "equivalence": "equivalent"
            }
          ],
          "code": "169413002",
          "display": "Hormone therapy (procedure)"
        },
        {
          "target": [
            {
              "code": "IM",
              "display": "Immun-/Antikoerpertherapie",
              "equivalence": "narrower",
              "comment": "SNOMED 897713009 wird sowohl fuer IM als auch fuer CI und CIZ verwendet; hier wird IM als Standardziel gewaehlt"
            }
          ],
          "code": "897713009",
          "display": "Immunotherapy (procedure)"
        },
        {
          "target": [
            {
              "code": "ZS",
              "display": "zielgerichtete Substanzen",
              "equivalence": "narrower",
              "comment": "SNOMED 1255831008 wird sowohl fuer ZS als auch CZ verwendet; hier wird ZS als Standardziel gewaehlt"
            }
          ],
          "code": "1255831008",
          "display": "Chemotherapy for malignant neoplastic disease using targeted agent (procedure)"
        },
        {
          "target": [
            {
              "code": "SZ",
              "display": "Stammzelltransplantation (inkl. Knochenmarktransplantation)",
              "equivalence": "equivalent"
            }
          ],
          "code": "1269349006",
          "display": "Transplantation of stem cell (procedure)"
        }
      ],
      "source": "http://snomed.info/sct",
      "target": "https://www.medizininformatik-initiative.de/fhir/ext/modul-onko/CodeSystem/mii-cs-onko-therapie-typ"
    }
  ],
  "version": "0.1.0",
  "status": "draft",
  "sourceUri": "http://snomed.info/sct",
  "targetUri": "https://www.medizininformatik-initiative.de/fhir/ext/modul-onko/CodeSystem/mii-cs-onko-therapie-typ"
}
